<?xml version="1.0" encoding="UTF-8"?>
<mxfile host="app.diagrams.net" modified="2022-04-26T16:33:48.587Z" agent="5.0 (Macintosh; Intel Mac OS X 10_15_7) AppleWebKit/537.36 (KHTML, like Gecko) Chrome/98.0.4758.102 Safari/537.36" etag="uLsma0TPwRJkLR6CMXIW" version="17.4.3">
  <diagram id="N0M3X1NWpZXYETuDEtgs" name="Page-1">
    <mxGraphModel dx="521" dy="517" grid="1" gridSize="10" guides="1" tooltips="1" connect="1" arrows="1" fold="1" page="1" pageScale="1" pageWidth="850" pageHeight="1100" math="0" shadow="0">
      <root>
        <mxCell id="0" />
        <mxCell id="1" parent="0" />
        <mxCell id="-cr9AeD9d8haLS9dOWXz-1" value="" style="rounded=0;whiteSpace=wrap;html=1;" vertex="1" parent="1">
          <mxGeometry x="80" y="80" width="40" height="40" as="geometry" />
        </mxCell>
        <mxCell id="-cr9AeD9d8haLS9dOWXz-2" value="" style="rounded=0;whiteSpace=wrap;html=1;fillColor=#f8cecc;strokeColor=#b85450;" vertex="1" parent="1">
          <mxGeometry x="160" y="80" width="40" height="40" as="geometry" />
        </mxCell>
        <mxCell id="-cr9AeD9d8haLS9dOWXz-3" value="" style="rounded=0;whiteSpace=wrap;html=1;" vertex="1" parent="1">
          <mxGeometry x="80" y="130" width="40" height="40" as="geometry" />
        </mxCell>
        <mxCell id="-cr9AeD9d8haLS9dOWXz-4" value="" style="rounded=0;whiteSpace=wrap;html=1;fillColor=#f8cecc;strokeColor=#b85450;" vertex="1" parent="1">
          <mxGeometry x="160" y="130" width="40" height="40" as="geometry" />
        </mxCell>
      </root>
    </mxGraphModel>
  </diagram>
</mxfile>
